openbrush/__init__.py
openbrush/__version__.py
openbrush/export.py
openbrush/tilt.py
openbrush/unpack.py
openbrush-0.2.data/scripts/analyze_tilt.py
openbrush-0.2.data/scripts/concatenate_tilt.py
openbrush-0.2.data/scripts/dump_tilt.py
openbrush-0.2.data/scripts/geometry_json_to_fbx.py
openbrush-0.2.data/scripts/geometry_json_to_obj.py
openbrush-0.2.data/scripts/normalize_sketch.py
openbrush-0.2.data/scripts/tilt_to_strokes_dae.py
openbrush-0.2.data/scripts/unpack_tilt.py
openbrush-0.2.dist-info/LICENSE
openbrush-0.2.dist-info/METADATA
openbrush-0.2.dist-info/WHEEL
openbrush-0.2.dist-info/top_level.txt
openbrush-0.2.dist-info/RECORD
